django_lab_members-0.3.0.dist-info/DESCRIPTION.rst
django_lab_members-0.3.0.dist-info/METADATA
django_lab_members-0.3.0.dist-info/RECORD
django_lab_members-0.3.0.dist-info/WHEEL
django_lab_members-0.3.0.dist-info/metadata.json
django_lab_members-0.3.0.dist-info/top_level.txt
lab_members/__init__.py
lab_members/admin.py
lab_members/models.py
lab_members/tests.py
lab_members/urls.py
lab_members/views.py
lab_members/static/lab_members/app.css
lab_members/static/lab_members/app.js
lab_members/static/lab_members/jquery.matchHeight-min.js
lab_members/templates/lab_members/_advisors_loop_item.html
lab_members/templates/lab_members/_alumni.html
lab_members/templates/lab_members/_education.html
lab_members/templates/lab_members/_employment.html
lab_members/templates/lab_members/_navbar.html
lab_members/templates/lab_members/_personal.html
lab_members/templates/lab_members/_research.html
lab_members/templates/lab_members/_scientist_list_item.html
lab_members/templates/lab_members/_sidebar.html
lab_members/templates/lab_members/base.html
lab_members/templates/lab_members/scientist_detail.html
lab_members/templates/lab_members/scientist_list.html
