Metadata-Version: 2.0
Name: django-lab-members
Version: 0.3.0
Summary: A Django app to display lab personnel and information about them.
Home-page: https://github.com/mfcovington/django-lab-members
Author: Michael F. Covington
Author-email: mfcovington@gmail.com
License: BSD License
Platform: UNKNOWN
Classifier: Development Status :: 3 - Alpha
Classifier: Environment :: Web Environment
Classifier: Framework :: Django
Classifier: Framework :: Django :: 1.7
Classifier: Framework :: Django :: 1.8
Classifier: Intended Audience :: Developers
Classifier: Intended Audience :: Science/Research
Classifier: License :: OSI Approved :: BSD License
Classifier: Operating System :: OS Independent
Classifier: Programming Language :: Python
Classifier: Programming Language :: Python :: 3
Classifier: Programming Language :: Python :: 3.2
Classifier: Programming Language :: Python :: 3.3
Classifier: Programming Language :: Python :: 3.4
Classifier: Programming Language :: Python :: 3 :: Only
Classifier: Topic :: Internet :: WWW/HTTP
Classifier: Topic :: Internet :: WWW/HTTP :: Dynamic Content
Requires-Dist: Django (>=1.7)
Requires-Dist: django-filer (>=0.9.10)
Requires-Dist: django-friendly-tag-loader (>=1.2)
Requires-Dist: django-sekizai (>=0.8.1)
